multicor_fa/__init__.py
multicor_fa/_em.py
multicor_fa/gsea.py
multicor_fa/mcfa_model.py
multicor_fa/simulate_model_gaussian.py
multicor_fa-1.0.2.dist-info/LICENSE
multicor_fa-1.0.2.dist-info/METADATA
multicor_fa-1.0.2.dist-info/WHEEL
multicor_fa-1.0.2.dist-info/top_level.txt
multicor_fa-1.0.2.dist-info/RECORD
