Metadata-Version: 2.1
Name: multicor-fa
Version: 1.0.2
Summary: Multiset Correlation and Factor Analysis
Author-email: "Brielin C. Brown" <bbrown@nygenome.org>, Collin Wang <cwang@nygenome.org>
License: BSD-3-Clause
Project-URL: Homepage, https://github.com/collinwa/MCFA
Project-URL: Bug Tracker, https://github.com/collinwa/MCFA/issues
Classifier: Programming Language :: Python :: 3
Classifier: Operating System :: OS Independent
Requires-Python: >=3.8
License-File: LICENSE
Requires-Dist: torch >=1.11
Requires-Dist: numpy >=1.20
Requires-Dist: pandas >=1.3.5
Requires-Dist: scipy >=1.7.1
Requires-Dist: scikit-learn >=1.0
